.project
.pydevproject
MANIFEST.in
README.txt
buildout.cfg
setup.py
docs/HISTORY.txt
docs/README.txt
src/ztfy/__init__.py
src/ztfy.alchemy.egg-info/PKG-INFO
src/ztfy.alchemy.egg-info/SOURCES.txt
src/ztfy.alchemy.egg-info/dependency_links.txt
src/ztfy.alchemy.egg-info/entry_points.txt
src/ztfy.alchemy.egg-info/namespace_packages.txt
src/ztfy.alchemy.egg-info/not-zip-safe
src/ztfy.alchemy.egg-info/requires.txt
src/ztfy.alchemy.egg-info/top_level.txt
src/ztfy/alchemy/__init__.py
src/ztfy/alchemy/configure.zcml
src/ztfy/alchemy/datamanager.py
src/ztfy/alchemy/engine.py
src/ztfy/alchemy/geotypes.py
src/ztfy/alchemy/interfaces.py
src/ztfy/alchemy/meta.zcml
src/ztfy/alchemy/metaconfigure.py
src/ztfy/alchemy/metadirectives.py
src/ztfy/alchemy/vocabulary.py
src/ztfy/alchemy/browser/__init__.py
src/ztfy/alchemy/browser/configure.zcml
src/ztfy/alchemy/doctests/README.txt
src/ztfy/alchemy/locales/ztfy.alchemy.pot
src/ztfy/alchemy/locales/en/LC_MESSAGES/ztfy.alchemy.mo
src/ztfy/alchemy/locales/en/LC_MESSAGES/ztfy.alchemy.po
src/ztfy/alchemy/locales/fr/LC_MESSAGES/ztfy.alchemy.mo
src/ztfy/alchemy/locales/fr/LC_MESSAGES/ztfy.alchemy.po
src/ztfy/alchemy/tests/__init__.py
src/ztfy/alchemy/tests/test_utilsdocs.py
src/ztfy/alchemy/tests/test_utilsdocstrings.py